myccm/__init__.py
myccm/ccm.py
myccm/fnn.py
myccm-5.0.dist-info/METADATA
myccm-5.0.dist-info/WHEEL
myccm-5.0.dist-info/top_level.txt
myccm-5.0.dist-info/RECORD
