Metadata-Version: 2.1
Name: myccm
Version: 5.0
Summary: This is a causal inference method
Home-page: https://github.com/zhougang2020/CCM
Author: Gang Zhou
Author-email: zg_pem@163.com
License: UNKNOWN
Platform: any
Requires-Python: >=3.5.0
